vietnamese.py
vietnamese-0.0.8.dist-info/METADATA
vietnamese-0.0.8.dist-info/WHEEL
vietnamese-0.0.8.dist-info/top_level.txt
vietnamese-0.0.8.dist-info/RECORD
