Metadata-Version: 2.1
Name: vietnamese
Version: 0.0.8
Summary: Basic resource for Vietnamese NLP.
Home-page: https://trituenhantao.io
License: UNKNOWN
Platform: UNKNOWN
